{"mc":{
	"DestroyA":{
		"frameRate":24,
		"events":[
			
			],
		"frames":[
			
			{
			"res":"BF43B498",
			"x":0,
			"y":132
			},
			{
			"res":"81160DA9",
			"x":0,
			"y":112
			},
			{
			"res":"B4E17F34",
			"x":0,
			"y":93
			},
			{
			"res":"3937B2A4",
			"x":0,
			"y":73
			},
			{
			"res":"B9E2F84A",
			"x":0,
			"y":54
			},
			{
			"res":"25E9A183",
			"x":0,
			"y":34
			},
			{
			"res":"83046B49",
			"x":0,
			"y":15
			},
			{
			"res":"2E36B9C",
			"x":0,
			"y":0
			}
			]
}},
	"res":{
		"25E9A183":{"x":1003,"y":0,"w":490,"h":821},
		"81160DA9":{"x":502,"y":861,"w":454,"h":668},
		"3937B2A4":{"x":1495,"y":785,"w":472,"h":745},
		"83046B49":{"x":502,"y":0,"w":499,"h":859},
		"2E36B9C":{"x":0,"y":0,"w":500,"h":889},
		"B9E2F84A":{"x":1495,"y":0,"w":481,"h":783},
		"BF43B498":{"x":0,"y":891,"w":445,"h":629},
		"B4E17F34":{"x":1003,"y":823,"w":463,"h":706}
	}}